ansar/__init__.py
ansar/bind.py
ansar/codec.py
ansar/convert.py
ansar/file.py
ansar/folder.py
ansar/json.py
ansar/lmx.py
ansar/memory.py
ansar/message.py
ansar/runtime.py
ansar/version.py
ansar/zed.py
ansar-1.0.86.dist-info/METADATA
ansar-1.0.86.dist-info/WHEEL
ansar-1.0.86.dist-info/top_level.txt
ansar-1.0.86.dist-info/RECORD
