Metadata-Version: 2.1
Name: ansar
Version: 1.0.86
Summary: Library for storing complex application objects in JSON files.
Home-page: https://gitlab.com/scott.ansar/ansar
Author: Scott Woods
Author-email: scott.suzuki@gmail.com
License: UNKNOWN
Download-URL: https://gitlab.com/scott.ansar/ansar/archive/1.0.86.tar.gz
Keywords: persistence,serialization,marshalling,encoding
Platform: UNKNOWN
Classifier: Programming Language :: Python :: 3.5
Classifier: License :: OSI Approved :: MIT License
Classifier: Operating System :: OS Independent
Requires-Dist: defusedxml (>=0.6)
